.coveragerc
.travis.yml
AUTHORS
ChangeLog
LICENSE
MANIFEST.in
README.rst
requirements.txt
setup.cfg
setup.py
tox.ini
docs/Makefile
docs/make.bat
docs/source/conf.py
docs/source/index.rst
docs/source/readme.rst
leonardo_channels/__init__.py
leonardo_channels/auth.py
leonardo_channels/default_settings.py
leonardo_channels/models.py
leonardo_channels/router.py
leonardo_channels/routes.py
leonardo_channels/routing.py
leonardo_channels/settings.py
leonardo_channels/utils.py
leonardo_channels.egg-info/PKG-INFO
leonardo_channels.egg-info/SOURCES.txt
leonardo_channels.egg-info/dependency_links.txt
leonardo_channels.egg-info/not-zip-safe
leonardo_channels.egg-info/pbr.json
leonardo_channels.egg-info/requires.txt
leonardo_channels.egg-info/top_level.txt
leonardo_channels/consumers/__init__.py
leonardo_channels/consumers/base.py
leonardo_channels/managers/__init__.py
leonardo_channels/managers/base.py
leonardo_channels/managers/users.py
leonardo_channels/managers/backends/__init__.py
leonardo_channels/managers/backends/base.py
leonardo_channels/managers/backends/cache.py
leonardo_channels/messages/__init__.py
leonardo_channels/messages/consumers.py
leonardo_channels/messages/messages.py
leonardo_channels/messages/routing.py
leonardo_channels/senders/__init__.py
leonardo_channels/senders/base.py
leonardo_channels/signals/__init__.py
leonardo_channels/signals/consumers.py
leonardo_channels/signals/reciever.py
leonardo_channels/signals/routing.py
leonardo_channels/static/websocket/client.js
leonardo_channels/static/websocket/reconnecting-websocket.js
leonardo_channels/widgets/__init__.py
leonardo_channels/widgets/consumers.py
leonardo_channels/widgets/reciever.py
leonardo_channels/widgets/routing.py
leonardo_channels/widgets/utils.py
requirements/default.txt
requirements/redis.txt
requirements/tests.txt
tests/cov.sh
tests/local_settings.py
tests/manage.py
tests/testapp/__init__.py
tests/testapp/models.py
tests/testapp/settings.py
tests/testapp/urls.py
tests/testapp/tests/__init__.py
tests/testapp/tests/test_commands.py